statshouse-0.2.3.dist-info/METADATA
statshouse-0.2.3.dist-info/WHEEL
statshouse-0.2.3.dist-info/licenses/LICENSE
statshouse/__init__.py
statshouse/_statshouse.py
statshouse-0.2.3.dist-info/RECORD
