Metadata-Version: 2.1
Name: statshouse
Version: 0.2.3
Summary: StatsHouse client library for Python
Author-Email: Gregory Petrosyan <pgregory@pgregory.net>
License: MPL-2.0
Classifier: Programming Language :: Python :: 3
Classifier: License :: OSI Approved :: Mozilla Public License 2.0 (MPL 2.0)
Classifier: Operating System :: OS Independent
Classifier: Intended Audience :: Developers
Classifier: Topic :: System :: Monitoring
Project-URL: Homepage, https://github.com/VKCOM/statshouse-py
Project-URL: Bug tracker, https://github.com/VKCOM/statshouse-py/issues
Requires-Python: >=3.7
Requires-Dist: msgpack>=1.0.5
